manzpy.py
manzpy-0.0.1.dist-info/METADATA
manzpy-0.0.1.dist-info/WHEEL
manzpy-0.0.1.dist-info/top_level.txt
manzpy-0.0.1.dist-info/RECORD
