Metadata-Version: 2.1
Name: manzpy
Version: 0.0.1
Summary: Manz Test Package.
Home-page: UNKNOWN
Author: Manzoor Bin Mahmood
License: UNKNOWN
Platform: UNKNOWN
Classifier: Programming Language :: Python :: 3
Classifier: Operating System :: OS Independent
Requires-Python: >=3.6
